luigi_chromadb_target/__init__.py
luigi_chromadb_target/target.py
luigi_chromadb_target-1.0.0.dist-info/LICENSE
luigi_chromadb_target-1.0.0.dist-info/METADATA
luigi_chromadb_target-1.0.0.dist-info/WHEEL
luigi_chromadb_target-1.0.0.dist-info/top_level.txt
luigi_chromadb_target-1.0.0.dist-info/RECORD
