Metadata-Version: 2.1
Name: luigi-chromadb-target
Version: 1.0.0
Summary: A Luigi Target implementation using ChromaDB.
Author-email: Pawel Gasiorowski <p.gasiorowski@axent.pl>
License: Apache License
Project-URL: Homepage, https://github.com/axent-pl/luigi-chromadb-target
Project-URL: Bug Tracker, https://github.com/axent-pl/luigi-chromadb-target/issues
Keywords: luigi,chromadb,target
Classifier: Programming Language :: Python :: 3
Classifier: License :: OSI Approved :: Apache Software License
Classifier: Operating System :: OS Independent
Requires-Python: >=3.6
License-File: LICENSE
Requires-Dist: luigi
Requires-Dist: chromadb
